{"name":"build-javascript","namedChunkGroups":{"polyfill":{"name":"polyfill","assets":[{"name":"webpack-runtime-2c333986227b29e41528.js","size":4624},{"name":"polyfill-71878164df8e360d5b1b.js","size":85848}],"filteredAssets":0,"assetsSize":90472,"filteredAuxiliaryAssets":2,"auxiliaryAssetsSize":226313},"app":{"name":"app","assets":[{"name":"webpack-runtime-2c333986227b29e41528.js","size":4624},{"name":"framework-45960ddbfac4dbcf5ef7.js","size":128958},{"name":"app-11a864e985c44ae176d5.js","size":53171}],"filteredAssets":0,"assetsSize":186753,"filteredAuxiliaryAssets":3,"auxiliaryAssetsSize":558801},"component---src-pages-404-js":{"name":"component---src-pages-404-js","assets":[{"name":"component---src-pages-404-js-0ee12d374a6fe4c2ff90.js","size":283}],"filteredAssets":0,"assetsSize":283,"filteredAuxiliaryAssets":1,"auxiliaryAssetsSize":332},"component---src-pages-index-js":{"name":"component---src-pages-index-js","assets":[{"name":"styles.0dd9654376dacf764799.css","size":1304053},{"name":"component---src-pages-index-js-735bb5f810e442a88977.js","size":152153}],"filteredAssets":0,"assetsSize":1456206,"filteredAuxiliaryAssets":17,"auxiliaryAssetsSize":3659256}},"assetsByChunkName":{"polyfill":["webpack-runtime-2c333986227b29e41528.js","polyfill-71878164df8e360d5b1b.js"],"app":["webpack-runtime-2c333986227b29e41528.js","framework-45960ddbfac4dbcf5ef7.js","app-11a864e985c44ae176d5.js"],"component---src-pages-404-js":["component---src-pages-404-js-0ee12d374a6fe4c2ff90.js"],"component---src-pages-index-js":["styles.0dd9654376dacf764799.css","component---src-pages-index-js-735bb5f810e442a88977.js"]},"childAssetsByChunkName":{}}